datarobot_mlflow/__init__.py
datarobot_mlflow/azure_helper.py
datarobot_mlflow/datarobot_kv_helper.py
datarobot_mlflow/dr_mlflow_integration.py
datarobot_mlflow/drflow_cli.py
datarobot_mlflow-0.1.dev2.dist-info/METADATA
datarobot_mlflow-0.1.dev2.dist-info/WHEEL
datarobot_mlflow-0.1.dev2.dist-info/entry_points.txt
datarobot_mlflow-0.1.dev2.dist-info/top_level.txt
datarobot_mlflow-0.1.dev2.dist-info/RECORD
