Metadata-Version: 2.1
Name: datarobot-mlflow
Version: 0.1.dev2
Summary: datarobot-mlflow client to synchronize an MLFlow model with DataRobot model
Home-page: https://datarobot.com
Author: DataRobot
Author-email: support+mlflow@datarobot.com
Maintainer: DataRobot
Maintainer-email: info+mlflow@datarobot.com
License: DataRobot Tool and Utility Agreement
Classifier: Programming Language :: Python :: 3
Classifier: Programming Language :: Python :: 3.7
Classifier: Programming Language :: Python :: 3.8
Classifier: Programming Language :: Python :: 3.9
Classifier: Programming Language :: Python :: 3.10
Classifier: License :: Other/Proprietary License
Classifier: Operating System :: MacOS
Classifier: Operating System :: POSIX
Classifier: Operating System :: Unix
Requires-Python: >=3.7
Requires-Dist: mlflow (>=1.0)
Requires-Dist: requests
Provides-Extra: azure
Requires-Dist: azure-ai-ml ; extra == 'azure'
Requires-Dist: azureml-mlflow ; extra == 'azure'
